.gitignore
.travis.yml
MANIFEST.in
README.rst
bootstrap.py
buildout.cfg
project.sublime-project
pytest.ini
setup.cfg
setup.py
versions.cfg
docs/HISTORY.txt
docs/LICENSE.txt
rbco/__init__.py
rbco.caseclasses.egg-info/PKG-INFO
rbco.caseclasses.egg-info/SOURCES.txt
rbco.caseclasses.egg-info/dependency_links.txt
rbco.caseclasses.egg-info/namespace_packages.txt
rbco.caseclasses.egg-info/not-zip-safe
rbco.caseclasses.egg-info/requires.txt
rbco.caseclasses.egg-info/top_level.txt
rbco/caseclasses/__init__.py