Metadata-Version: 1.1
Name: rbco.caseclasses
Version: 1.0.0
Summary: Provide a compact syntax to define simple "struct-like" (or "record-like", "bean-like") classes.
Home-page: https://github.com/rafaelbco/rbco.caseclasses
Author: Rafael Oliveira
Author-email: rafaelbco@gmail.com
License: MIT
Keywords: caseclasses
Platform: UNKNOWN
Classifier: Programming Language :: Python :: 2.7
Classifier: Programming Language :: Python
Classifier: Topic :: Software Development :: Libraries :: Python Modules
